drawnow/__init__.py
drawnow/drawnow.py
drawnow-0.72.5.dist-info/METADATA
drawnow-0.72.5.dist-info/WHEEL
drawnow-0.72.5.dist-info/top_level.txt
drawnow-0.72.5.dist-info/RECORD
