Metadata-Version: 2.1
Name: drawnow
Version: 0.72.5
Summary: MATLAB-like drawnow
Home-page: https://github.com/stsievert/python-drawnow
Author: Scott Sievert
Author-email: dev@stsievert.com
License: UNKNOWN
Download-URL: https://github.com/stsievert/python-drawnow/archive/master.zip
Keywords: figure,plotting,visualization,matlab
Platform: UNKNOWN
Classifier: Intended Audience :: Science/Research
Classifier: License :: OSI Approved :: MIT License
Classifier: Natural Language :: English
Classifier: Operating System :: OS Independent
Classifier: Programming Language :: Python
Classifier: Topic :: Scientific/Engineering
Classifier: Topic :: Scientific/Engineering :: Visualization
Requires: matplotlib
